setlexsem/__init__.py
setlexsem/constants.py
setlexsem/utils.py
setlexsem/analyze/__init__.py
setlexsem/analyze/error_analysis.py
setlexsem/analyze/hypothesis_testing_utils.py
setlexsem/analyze/visualize.py
setlexsem/experiment/__init__.py
setlexsem/experiment/experiment.py
setlexsem/experiment/lmapi.py
setlexsem/experiment/run_experiments.py
setlexsem/generate/__init__.py
setlexsem/generate/generate_prompts.py
setlexsem/generate/generate_sets.py
setlexsem/generate/prompt.py
setlexsem/generate/sample.py
setlexsem/generate/utils_io.py
setlexsem/prepare/__init__.py
setlexsem/prepare/download.py
setlexsem/prepare/percentiles.py
setlexsem-0.0.2.dist-info/LICENSE
setlexsem-0.0.2.dist-info/METADATA
setlexsem-0.0.2.dist-info/NOTICE
setlexsem-0.0.2.dist-info/WHEEL
setlexsem-0.0.2.dist-info/top_level.txt
setlexsem-0.0.2.dist-info/RECORD
