Metadata-Version: 2.1
Name: setlexsem
Version: 0.0.2
License-File: LICENSE
License-File: NOTICE
Requires-Dist: tqdm
Requires-Dist: boto3
Requires-Dist: nltk
Requires-Dist: tiktoken
Requires-Dist: openai
Requires-Dist: pandas
Requires-Dist: pyyaml
Provides-Extra: dev
Requires-Dist: check-manifest; extra == "dev"
Requires-Dist: flake8; extra == "dev"
Requires-Dist: black; extra == "dev"
Provides-Extra: test
Requires-Dist: pytest; extra == "test"
Requires-Dist: coverage; extra == "test"
